sqlpiece/__init__.py
sqlpiece/SQLPieceBPE/__init__.py
sqlpiece/SQLPieceBPE/test_tokenizer.py
sqlpiece/SQLPieceBPE/tokenizer.py
sqlpiece/SQLPieceBPE/vocab/bpe_sql_vocab.json
sqlpiece/SQLPieceBPE/vocab/gpt2_merges.txt
sqlpiece/SQLPieceBPE/vocab/gpt2_vocab.json
sqlpiece/SQLPieceBPE/vocab/merges.txt
sqlpiece/SQLPieceBPE/vocab/sql_vocab.pkl
sqlpiece/SQLPieceBPE/vocab/vocab.json
sqlpiece/SQLPieceWPE/__init__.py
sqlpiece/SQLPieceWPE/lookup_dict.pkl
sqlpiece/SQLPieceWPE/no_morph_vocab.txt
sqlpiece/SQLPieceWPE/tokenizer.py
sqlpiece/SQLPieceWPE/with_morph_vocab.txt
sqlpiece-0.1.2.dist-info/METADATA
sqlpiece-0.1.2.dist-info/WHEEL
sqlpiece-0.1.2.dist-info/top_level.txt
sqlpiece-0.1.2.dist-info/RECORD
